{
  "artifact_type": "case_pipeline_status",
  "case_key": "case-20260415-cd803ba3",
  "completed_at": "2026-04-15T22:41:46.869002+00:00",
  "current_stage": "decision",
  "dispatch_id": "refresh-case-20260415-cd803ba3-20260415T224048Z",
  "helper_status": {
    "materialize_case_swarm_artifacts": {
      "attempted_at": "2026-04-15T22:41:47.032706+00:00",
      "helper": "materialize_case_swarm_artifacts",
      "ok": true,
      "payload": {
        "artifact_index": "qualitative-db/40-research/cases/case-20260415-cd803ba3/artifacts/index.json",
        "case_key": "case-20260415-cd803ba3",
        "dispatch_dir": "qualitative-db/40-research/cases/case-20260415-cd803ba3/researcher-analyses/2026-04-15/dispatch-case-20260415-cd803ba3-20260415T203927Z",
        "ok": true,
        "researcher_swarm_current": "qualitative-db/40-research/cases/case-20260415-cd803ba3/researcher-swarm-current.md",
        "researcher_swarm_summary": "qualitative-db/40-research/cases/case-20260415-cd803ba3/researcher-swarm-summary.md"
      },
      "returncode": 0
    },
    "post_case_terminal_topic_marker": {
      "attempted_at": "2026-04-15T22:41:17.705914+00:00",
      "helper": "post_case_terminal_topic_marker",
      "ok": true,
      "payload": {
        "case_key": "case-20260415-cd803ba3",
        "dispatch_id": "dispatch-case-20260415-cd803ba3-20260415T203927Z",
        "noop": true,
        "ok": true,
        "reason": "missing_topic_binding"
      },
      "returncode": 0
    }
  },
  "last_event": {
    "at": "2026-04-15T22:41:46.869002+00:00",
    "current_stage": "decision",
    "message": "Decision-Maker completed and packet rendered",
    "status": "pipeline_completed"
  },
  "market_id": "367ed8d7-c08e-4588-a449-c83aead47ec3",
  "market_title": "Will the price of Bitcoin be above $74,000 on April 17?",
  "runner_id": "run_decision_maker",
  "schema_version": "case-pipeline-status/v1",
  "stage_detail_states": {
    "decision": "completed",
    "dispatch": "completed",
    "swarm": "completed",
    "synthesis": "completed"
  },
  "stage_statuses": {
    "decision": "completed",
    "dispatch": "completed",
    "swarm": "completed",
    "synthesis": "completed"
  },
  "started_at": "2026-04-15T20:41:27.091712+00:00",
  "status": "pipeline_completed",
  "terminal_summary": {
    "decision_handoff_path": "qualitative-db/40-research/cases/case-20260415-cd803ba3/researcher-analyses/2026-04-15/dispatch-case-20260415-cd803ba3-20260415T203927Z/decision-handoff.md",
    "decision_packet_json": "qualitative-db/40-research/cases/case-20260415-cd803ba3/decision-maker/artifacts/decision-maker-packet.json",
    "decision_packet_markdown": "qualitative-db/40-research/cases/case-20260415-cd803ba3/decision-maker/decision-maker-packet.md",
    "decision_parse_attempt_count": 1,
    "decision_readiness": "ready",
    "decision_recovered_after_retry": false,
    "forecast_decision_persist_error": "",
    "forecast_decision_persisted": true,
    "position_policy": "hold_only",
    "raw_gateway_response_path": "roles/decision-maker/runtime/artifacts/case-20260415-cd803ba3/decision-gateway-response-refresh-case-20260415-cd803ba3-20260415T224048Z.json",
    "raw_response_text_path": "roles/decision-maker/runtime/artifacts/case-20260415-cd803ba3/decision-response-refresh-case-20260415-cd803ba3-20260415T224048Z.raw.txt",
    "recommended_side": "yes",
    "swarm_stage_status_path": "qualitative-db/40-research/cases/case-20260415-cd803ba3/researcher-analyses/2026-04-15/dispatch-case-20260415-cd803ba3-20260415T203927Z/swarm-stage-status.json",
    "synthesis_artifact_path": "qualitative-db/40-research/cases/case-20260415-cd803ba3/researcher-analyses/2026-04-15/dispatch-case-20260415-cd803ba3-20260415T203927Z/syndicated-finding.md",
    "trade_authorization": "watch_only"
  },
  "timeline": [
    {
      "at": "2026-04-15T20:41:27.091712+00:00",
      "current_stage": "swarm",
      "manifest_path": "/Users/agent2/.openclaw/orchestrator/roles/orchestrator/researchers-swarm-subagents/runtime/dispatch-manifests/dispatch-case-20260415-cd803ba3-20260415T203927Z.json",
      "message": "Fresh case claimed and dispatch launched",
      "status": "pipeline_started",
      "target_session_key": ""
    },
    {
      "at": "2026-04-15T20:41:27.572373+00:00",
      "current_stage": "swarm",
      "message": "Swarm stage reconciled",
      "status": "pipeline_in_progress"
    },
    {
      "at": "2026-04-15T20:41:43.214555+00:00",
      "current_stage": "swarm",
      "message": "Swarm stage reconciled",
      "status": "pipeline_in_progress"
    },
    {
      "at": "2026-04-15T20:41:58.579273+00:00",
      "current_stage": "swarm",
      "message": "Swarm stage reconciled",
      "status": "pipeline_in_progress"
    },
    {
      "at": "2026-04-15T20:42:14.029864+00:00",
      "current_stage": "swarm",
      "message": "Swarm stage reconciled",
      "status": "pipeline_in_progress"
    },
    {
      "at": "2026-04-15T20:42:21.442580+00:00",
      "current_stage": "swarm",
      "message": "Swarm stage reconciled",
      "status": "pipeline_in_progress"
    },
    {
      "at": "2026-04-15T20:42:29.429745+00:00",
      "current_stage": "swarm",
      "message": "Swarm stage reconciled",
      "status": "pipeline_in_progress"
    },
    {
      "at": "2026-04-15T20:42:44.898126+00:00",
      "current_stage": "swarm",
      "message": "Swarm stage reconciled",
      "status": "pipeline_in_progress"
    },
    {
      "at": "2026-04-15T20:43:00.431949+00:00",
      "current_stage": "swarm",
      "message": "Swarm stage reconciled",
      "status": "pipeline_in_progress"
    },
    {
      "at": "2026-04-15T20:43:15.988693+00:00",
      "current_stage": "swarm",
      "message": "Swarm stage reconciled",
      "status": "pipeline_in_progress"
    },
    {
      "at": "2026-04-15T20:43:22.061437+00:00",
      "current_stage": "swarm",
      "message": "Swarm stage reconciled",
      "status": "pipeline_in_progress"
    },
    {
      "at": "2026-04-15T20:43:31.540428+00:00",
      "current_stage": "swarm",
      "message": "Swarm stage reconciled",
      "status": "pipeline_in_progress"
    },
    {
      "at": "2026-04-15T20:43:47.116456+00:00",
      "current_stage": "swarm",
      "message": "Swarm stage reconciled",
      "status": "pipeline_in_progress"
    },
    {
      "at": "2026-04-15T20:44:02.686688+00:00",
      "current_stage": "swarm",
      "message": "Swarm stage reconciled",
      "status": "pipeline_in_progress"
    },
    {
      "at": "2026-04-15T20:44:18.240114+00:00",
      "current_stage": "swarm",
      "message": "Swarm stage reconciled",
      "status": "pipeline_in_progress"
    },
    {
      "at": "2026-04-15T20:44:22.667093+00:00",
      "current_stage": "swarm",
      "message": "Swarm stage reconciled",
      "status": "pipeline_in_progress"
    },
    {
      "at": "2026-04-15T20:44:33.886868+00:00",
      "current_stage": "swarm",
      "message": "Swarm stage reconciled",
      "status": "pipeline_in_progress"
    },
    {
      "at": "2026-04-15T20:44:49.438359+00:00",
      "current_stage": "swarm",
      "message": "Swarm stage reconciled",
      "status": "pipeline_in_progress"
    },
    {
      "at": "2026-04-15T20:45:04.995208+00:00",
      "current_stage": "swarm",
      "message": "Swarm stage reconciled",
      "status": "pipeline_in_progress"
    },
    {
      "at": "2026-04-15T20:45:20.556649+00:00",
      "current_stage": "swarm",
      "message": "Swarm stage reconciled",
      "status": "pipeline_in_progress"
    },
    {
      "at": "2026-04-15T20:45:23.257554+00:00",
      "current_stage": "swarm",
      "message": "Swarm stage reconciled",
      "status": "pipeline_in_progress"
    },
    {
      "at": "2026-04-15T20:45:36.126456+00:00",
      "current_stage": "swarm",
      "message": "Swarm stage reconciled",
      "status": "pipeline_in_progress"
    },
    {
      "at": "2026-04-15T20:45:51.688249+00:00",
      "current_stage": "swarm",
      "message": "Swarm stage reconciled",
      "status": "pipeline_in_progress"
    },
    {
      "at": "2026-04-15T20:46:07.224247+00:00",
      "current_stage": "swarm",
      "message": "Swarm stage reconciled",
      "status": "pipeline_in_progress"
    },
    {
      "at": "2026-04-15T20:46:22.778393+00:00",
      "current_stage": "swarm",
      "message": "Swarm stage reconciled",
      "status": "pipeline_in_progress"
    },
    {
      "at": "2026-04-15T20:46:23.847811+00:00",
      "current_stage": "swarm",
      "message": "Swarm stage reconciled",
      "status": "pipeline_in_progress"
    },
    {
      "at": "2026-04-15T20:46:38.334368+00:00",
      "current_stage": "synthesis",
      "message": "Swarm stage reconciled",
      "status": "pipeline_in_progress"
    },
    {
      "at": "2026-04-15T20:46:39.000633+00:00",
      "current_stage": "swarm",
      "message": "Synthesis launch check is still waiting for researcher sidecars",
      "status": "pipeline_in_progress"
    },
    {
      "at": "2026-04-15T20:46:39.260738+00:00",
      "current_stage": "swarm",
      "message": "Synthesis launch check is still waiting for researcher sidecars",
      "status": "pipeline_in_progress"
    },
    {
      "at": "2026-04-15T20:46:54.517972+00:00",
      "current_stage": "synthesis",
      "message": "Swarm stage reconciled",
      "status": "pipeline_in_progress"
    },
    {
      "at": "2026-04-15T20:46:54.950437+00:00",
      "current_stage": "swarm",
      "message": "Synthesis launch check is still waiting for researcher sidecars",
      "status": "pipeline_in_progress"
    },
    {
      "at": "2026-04-15T20:46:55.308198+00:00",
      "current_stage": "swarm",
      "message": "Synthesis launch check is still waiting for researcher sidecars",
      "status": "pipeline_in_progress"
    },
    {
      "at": "2026-04-15T20:47:11.097672+00:00",
      "current_stage": "synthesis",
      "message": "Swarm stage reconciled",
      "status": "pipeline_in_progress"
    },
    {
      "at": "2026-04-15T20:47:11.888012+00:00",
      "current_stage": "synthesis",
      "launch_reason": "already_launching",
      "message": "Synthesis launch is already in progress",
      "status": "pipeline_in_progress"
    },
    {
      "at": "2026-04-15T20:47:12.551360+00:00",
      "current_stage": "synthesis",
      "launch_reason": "already_launching",
      "message": "Synthesis launch is already in progress",
      "status": "pipeline_in_progress"
    },
    {
      "at": "2026-04-15T20:47:24.414508+00:00",
      "current_stage": "synthesis",
      "message": "Swarm stage reconciled",
      "status": "pipeline_in_progress"
    },
    {
      "at": "2026-04-15T20:47:24.582356+00:00",
      "current_stage": "synthesis",
      "launch_reason": "already_running",
      "message": "Synthesis launch is already in progress",
      "status": "pipeline_in_progress"
    },
    {
      "at": "2026-04-15T20:47:24.754511+00:00",
      "current_stage": "synthesis",
      "launch_reason": "already_running",
      "message": "Synthesis launch is already in progress",
      "status": "pipeline_in_progress"
    },
    {
      "at": "2026-04-15T20:47:27.967418+00:00",
      "current_stage": "synthesis",
      "message": "Swarm stage reconciled",
      "status": "pipeline_in_progress"
    },
    {
      "at": "2026-04-15T20:47:28.155798+00:00",
      "current_stage": "synthesis",
      "launch_reason": "already_running",
      "message": "Synthesis launch is already in progress",
      "status": "pipeline_in_progress"
    },
    {
      "at": "2026-04-15T20:47:28.321710+00:00",
      "current_stage": "synthesis",
      "launch_reason": "already_running",
      "message": "Synthesis launch is already in progress",
      "status": "pipeline_in_progress"
    },
    {
      "at": "2026-04-15T20:47:43.725115+00:00",
      "current_stage": "synthesis",
      "message": "Swarm stage reconciled",
      "status": "pipeline_in_progress"
    },
    {
      "at": "2026-04-15T20:47:43.957544+00:00",
      "current_stage": "synthesis",
      "launch_reason": "already_running",
      "message": "Synthesis launch is already in progress",
      "status": "pipeline_in_progress"
    },
    {
      "at": "2026-04-15T20:47:44.146390+00:00",
      "current_stage": "synthesis",
      "launch_reason": "already_running",
      "message": "Synthesis launch is already in progress",
      "status": "pipeline_in_progress"
    },
    {
      "at": "2026-04-15T20:47:59.485965+00:00",
      "current_stage": "synthesis",
      "message": "Swarm stage reconciled",
      "status": "pipeline_in_progress"
    },
    {
      "at": "2026-04-15T20:47:59.660853+00:00",
      "current_stage": "synthesis",
      "launch_reason": "already_running",
      "message": "Synthesis launch is already in progress",
      "status": "pipeline_in_progress"
    },
    {
      "at": "2026-04-15T20:47:59.822866+00:00",
      "current_stage": "synthesis",
      "launch_reason": "already_running",
      "message": "Synthesis launch is already in progress",
      "status": "pipeline_in_progress"
    },
    {
      "at": "2026-04-15T20:48:15.451224+00:00",
      "current_stage": "synthesis",
      "message": "Swarm stage reconciled",
      "status": "pipeline_in_progress"
    },
    {
      "at": "2026-04-15T20:48:15.707960+00:00",
      "current_stage": "synthesis",
      "launch_reason": "already_running",
      "message": "Synthesis launch is already in progress",
      "status": "pipeline_in_progress"
    },
    {
      "at": "2026-04-15T20:48:15.940174+00:00",
      "current_stage": "synthesis",
      "launch_reason": "already_running",
      "message": "Synthesis launch is already in progress",
      "status": "pipeline_in_progress"
    },
    {
      "at": "2026-04-15T20:48:25.369239+00:00",
      "current_stage": "synthesis",
      "message": "Swarm stage reconciled",
      "status": "pipeline_in_progress"
    },
    {
      "at": "2026-04-15T20:48:25.684223+00:00",
      "current_stage": "synthesis",
      "launch_reason": "already_running",
      "message": "Synthesis launch is already in progress",
      "status": "pipeline_in_progress"
    },
    {
      "at": "2026-04-15T20:48:25.897037+00:00",
      "current_stage": "synthesis",
      "launch_reason": "already_running",
      "message": "Synthesis launch is already in progress",
      "status": "pipeline_in_progress"
    },
    {
      "at": "2026-04-15T20:48:32.325782+00:00",
      "current_stage": "synthesis",
      "message": "Swarm stage reconciled",
      "status": "pipeline_in_progress"
    },
    {
      "at": "2026-04-15T20:48:32.609347+00:00",
      "current_stage": "synthesis",
      "launch_reason": "already_running",
      "message": "Synthesis launch is already in progress",
      "status": "pipeline_in_progress"
    },
    {
      "at": "2026-04-15T20:48:32.832629+00:00",
      "current_stage": "synthesis",
      "launch_reason": "already_running",
      "message": "Synthesis launch is already in progress",
      "status": "pipeline_in_progress"
    },
    {
      "at": "2026-04-15T20:48:48.284272+00:00",
      "current_stage": "synthesis",
      "message": "Swarm stage reconciled",
      "status": "pipeline_in_progress"
    },
    {
      "at": "2026-04-15T20:48:48.502210+00:00",
      "current_stage": "synthesis",
      "launch_reason": "already_running",
      "message": "Synthesis launch is already in progress",
      "status": "pipeline_in_progress"
    },
    {
      "at": "2026-04-15T20:48:48.692575+00:00",
      "current_stage": "synthesis",
      "launch_reason": "already_running",
      "message": "Synthesis launch is already in progress",
      "status": "pipeline_in_progress"
    },
    {
      "at": "2026-04-15T20:48:58.127632+00:00",
      "current_stage": "synthesis",
      "message": "Synthesis completed and decision handoff is ready",
      "status": "pipeline_in_progress"
    },
    {
      "at": "2026-04-15T20:49:04.067967+00:00",
      "current_stage": "decision",
      "message": "Swarm stage reconciled",
      "status": "pipeline_in_progress"
    },
    {
      "at": "2026-04-15T20:49:05.352022+00:00",
      "current_stage": "decision",
      "message": "Decision-Maker launch claimed and worker subprocess started",
      "recovered_stale_claim": false,
      "status": "pipeline_in_progress"
    },
    {
      "at": "2026-04-15T20:49:12.227035+00:00",
      "current_stage": "decision",
      "message": "Decision-Maker stage started",
      "status": "pipeline_in_progress"
    },
    {
      "at": "2026-04-15T20:49:21.385309+00:00",
      "current_stage": "decision",
      "message": "Swarm stage reconciled",
      "status": "pipeline_in_progress"
    },
    {
      "at": "2026-04-15T20:49:26.448342+00:00",
      "current_stage": "decision",
      "message": "Swarm stage reconciled",
      "status": "pipeline_in_progress"
    },
    {
      "at": "2026-04-15T20:49:36.903314+00:00",
      "current_stage": "decision",
      "message": "Swarm stage reconciled",
      "status": "pipeline_in_progress"
    },
    {
      "at": "2026-04-15T20:49:52.391353+00:00",
      "current_stage": "decision",
      "message": "Swarm stage reconciled",
      "status": "pipeline_in_progress"
    },
    {
      "at": "2026-04-15T20:49:52.608054+00:00",
      "current_stage": "decision",
      "message": "Watchdog finalized pipeline from ready decision artifacts",
      "status": "pipeline_completed"
    },
    {
      "at": "2026-04-15T20:49:56.787120+00:00",
      "current_stage": "decision",
      "message": "Decision-Maker completed and packet rendered",
      "status": "pipeline_completed"
    },
    {
      "at": "2026-04-15T22:41:13.438084+00:00",
      "current_stage": "decision",
      "message": "Decision-Maker stage started",
      "status": "pipeline_in_progress"
    },
    {
      "at": "2026-04-15T22:41:16.927887+00:00",
      "current_stage": "decision",
      "message": "Swarm stage reconciled",
      "status": "pipeline_in_progress"
    },
    {
      "at": "2026-04-15T22:41:17.323314+00:00",
      "current_stage": "decision",
      "message": "Watchdog finalized pipeline from ready decision artifacts",
      "status": "pipeline_completed"
    },
    {
      "at": "2026-04-15T22:41:46.869002+00:00",
      "current_stage": "decision",
      "message": "Decision-Maker completed and packet rendered",
      "status": "pipeline_completed"
    }
  ],
  "updated_at": "2026-04-15T22:41:46.869002+00:00"
}
