{
  "artifact_type": "case_pipeline_status",
  "case_key": "case-20260414-4ed80a0a",
  "completed_at": "2026-04-14T17:51:05.300460+00:00",
  "current_stage": "decision",
  "dispatch_id": "dispatch-case-20260414-4ed80a0a-20260414T174040Z",
  "helper_status": {
    "materialize_case_swarm_artifacts": {
      "attempted_at": "2026-04-14T17:51:05.475774+00:00",
      "helper": "materialize_case_swarm_artifacts",
      "ok": true,
      "payload": {
        "artifact_index": "qualitative-db/40-research/cases/case-20260414-4ed80a0a/artifacts/index.json",
        "case_key": "case-20260414-4ed80a0a",
        "dispatch_dir": "qualitative-db/40-research/cases/case-20260414-4ed80a0a/researcher-analyses/2026-04-14/dispatch-case-20260414-4ed80a0a-20260414T174040Z",
        "ok": true,
        "researcher_swarm_current": "qualitative-db/40-research/cases/case-20260414-4ed80a0a/researcher-swarm-current.md",
        "researcher_swarm_summary": "qualitative-db/40-research/cases/case-20260414-4ed80a0a/researcher-swarm-summary.md"
      },
      "returncode": 0
    },
    "post_case_terminal_topic_marker": {
      "attempted_at": "2026-04-14T17:51:05.635556+00:00",
      "helper": "post_case_terminal_topic_marker",
      "ok": true,
      "payload": {
        "case_key": "case-20260414-4ed80a0a",
        "dispatch_id": "dispatch-case-20260414-4ed80a0a-20260414T174040Z",
        "noop": true,
        "ok": true,
        "reason": "missing_topic_binding"
      },
      "returncode": 0
    }
  },
  "last_event": {
    "at": "2026-04-14T17:51:05.300460+00:00",
    "current_stage": "decision",
    "message": "Decision-Maker completed and packet rendered",
    "status": "pipeline_completed"
  },
  "market_id": "388995c3-1866-46a6-9793-69442db90054",
  "market_title": "Will Ethereum reach $2,400 April 13-19?",
  "runner_id": "run_decision_maker",
  "schema_version": "case-pipeline-status/v1",
  "stage_detail_states": {
    "decision": "completed",
    "dispatch": "completed",
    "swarm": "completed",
    "synthesis": "completed"
  },
  "stage_statuses": {
    "decision": "completed",
    "dispatch": "completed",
    "swarm": "completed",
    "synthesis": "completed"
  },
  "started_at": "2026-04-14T17:42:29.133551+00:00",
  "status": "pipeline_completed",
  "terminal_summary": {
    "decision_handoff_path": "qualitative-db/40-research/cases/case-20260414-4ed80a0a/researcher-analyses/2026-04-14/dispatch-case-20260414-4ed80a0a-20260414T174040Z/decision-handoff.md",
    "decision_packet_json": "qualitative-db/40-research/cases/case-20260414-4ed80a0a/decision-maker/artifacts/decision-maker-packet.json",
    "decision_packet_markdown": "qualitative-db/40-research/cases/case-20260414-4ed80a0a/decision-maker/decision-maker-packet.md",
    "decision_parse_attempt_count": 1,
    "decision_readiness": "ready",
    "decision_recovered_after_retry": false,
    "forecast_decision_persist_error": "",
    "forecast_decision_persisted": true,
    "position_policy": "hold_only",
    "raw_gateway_response_path": "roles/decision-maker/runtime/artifacts/case-20260414-4ed80a0a/decision-gateway-response-dispatch-case-20260414-4ed80a0a-20260414T174040Z.json",
    "raw_response_text_path": "roles/decision-maker/runtime/artifacts/case-20260414-4ed80a0a/decision-response-dispatch-case-20260414-4ed80a0a-20260414T174040Z.raw.txt",
    "recommended_side": "yes",
    "swarm_stage_status_path": "qualitative-db/40-research/cases/case-20260414-4ed80a0a/researcher-analyses/2026-04-14/dispatch-case-20260414-4ed80a0a-20260414T174040Z/swarm-stage-status.json",
    "synthesis_artifact_path": "qualitative-db/40-research/cases/case-20260414-4ed80a0a/researcher-analyses/2026-04-14/dispatch-case-20260414-4ed80a0a-20260414T174040Z/syndicated-finding.md",
    "trade_authorization": "watch_only"
  },
  "timeline": [
    {
      "at": "2026-04-14T17:42:29.133551+00:00",
      "current_stage": "swarm",
      "manifest_path": "/Users/agent2/.openclaw/orchestrator/roles/orchestrator/researchers-swarm-subagents/runtime/dispatch-manifests/dispatch-case-20260414-4ed80a0a-20260414T174040Z.json",
      "message": "Fresh case claimed and dispatch launched",
      "status": "pipeline_started",
      "target_session_key": ""
    },
    {
      "at": "2026-04-14T17:42:29.405660+00:00",
      "current_stage": "swarm",
      "message": "Swarm stage reconciled",
      "status": "pipeline_in_progress"
    },
    {
      "at": "2026-04-14T17:42:44.831734+00:00",
      "current_stage": "swarm",
      "message": "Swarm stage reconciled",
      "status": "pipeline_in_progress"
    },
    {
      "at": "2026-04-14T17:43:00.299773+00:00",
      "current_stage": "swarm",
      "message": "Swarm stage reconciled",
      "status": "pipeline_in_progress"
    },
    {
      "at": "2026-04-14T17:43:02.250762+00:00",
      "current_stage": "swarm",
      "message": "Swarm stage reconciled",
      "status": "pipeline_in_progress"
    },
    {
      "at": "2026-04-14T17:43:15.741547+00:00",
      "current_stage": "swarm",
      "message": "Swarm stage reconciled",
      "status": "pipeline_in_progress"
    },
    {
      "at": "2026-04-14T17:43:31.168194+00:00",
      "current_stage": "swarm",
      "message": "Swarm stage reconciled",
      "status": "pipeline_in_progress"
    },
    {
      "at": "2026-04-14T17:43:46.609748+00:00",
      "current_stage": "swarm",
      "message": "Swarm stage reconciled",
      "status": "pipeline_in_progress"
    },
    {
      "at": "2026-04-14T17:44:02.051074+00:00",
      "current_stage": "swarm",
      "message": "Swarm stage reconciled",
      "status": "pipeline_in_progress"
    },
    {
      "at": "2026-04-14T17:44:02.640652+00:00",
      "current_stage": "swarm",
      "message": "Swarm stage reconciled",
      "status": "pipeline_in_progress"
    },
    {
      "at": "2026-04-14T17:44:17.500966+00:00",
      "current_stage": "swarm",
      "message": "Swarm stage reconciled",
      "status": "pipeline_in_progress"
    },
    {
      "at": "2026-04-14T17:44:33.035011+00:00",
      "current_stage": "swarm",
      "message": "Swarm stage reconciled",
      "status": "pipeline_in_progress"
    },
    {
      "at": "2026-04-14T17:44:48.538856+00:00",
      "current_stage": "swarm",
      "message": "Swarm stage reconciled",
      "status": "pipeline_in_progress"
    },
    {
      "at": "2026-04-14T17:45:03.016093+00:00",
      "current_stage": "swarm",
      "message": "Swarm stage reconciled",
      "status": "pipeline_in_progress"
    },
    {
      "at": "2026-04-14T17:45:03.879184+00:00",
      "current_stage": "swarm",
      "message": "Swarm stage reconciled",
      "status": "pipeline_in_progress"
    },
    {
      "at": "2026-04-14T17:45:19.377023+00:00",
      "current_stage": "swarm",
      "message": "Swarm stage reconciled",
      "status": "pipeline_in_progress"
    },
    {
      "at": "2026-04-14T17:45:34.901243+00:00",
      "current_stage": "swarm",
      "message": "Swarm stage reconciled",
      "status": "pipeline_in_progress"
    },
    {
      "at": "2026-04-14T17:45:50.421923+00:00",
      "current_stage": "swarm",
      "message": "Swarm stage reconciled",
      "status": "pipeline_in_progress"
    },
    {
      "at": "2026-04-14T17:46:03.594978+00:00",
      "current_stage": "swarm",
      "message": "Swarm stage reconciled",
      "status": "pipeline_in_progress"
    },
    {
      "at": "2026-04-14T17:46:05.971794+00:00",
      "current_stage": "swarm",
      "message": "Swarm stage reconciled",
      "status": "pipeline_in_progress"
    },
    {
      "at": "2026-04-14T17:46:21.433758+00:00",
      "current_stage": "swarm",
      "message": "Swarm stage reconciled",
      "status": "pipeline_in_progress"
    },
    {
      "at": "2026-04-14T17:46:36.907789+00:00",
      "current_stage": "swarm",
      "message": "Swarm stage reconciled",
      "status": "pipeline_in_progress"
    },
    {
      "at": "2026-04-14T17:46:52.435783+00:00",
      "current_stage": "swarm",
      "message": "Swarm stage reconciled",
      "status": "pipeline_in_progress"
    },
    {
      "at": "2026-04-14T17:47:04.162699+00:00",
      "current_stage": "swarm",
      "message": "Swarm stage reconciled",
      "status": "pipeline_in_progress"
    },
    {
      "at": "2026-04-14T17:47:07.972205+00:00",
      "current_stage": "swarm",
      "message": "Swarm stage reconciled",
      "status": "pipeline_in_progress"
    },
    {
      "at": "2026-04-14T17:47:23.517179+00:00",
      "current_stage": "swarm",
      "message": "Swarm stage reconciled",
      "status": "pipeline_in_progress"
    },
    {
      "at": "2026-04-14T17:47:39.053349+00:00",
      "current_stage": "swarm",
      "message": "Swarm stage reconciled",
      "status": "pipeline_in_progress"
    },
    {
      "at": "2026-04-14T17:47:54.585115+00:00",
      "current_stage": "swarm",
      "message": "Swarm stage reconciled",
      "status": "pipeline_in_progress"
    },
    {
      "at": "2026-04-14T17:48:04.747236+00:00",
      "current_stage": "synthesis",
      "message": "Swarm stage reconciled",
      "status": "pipeline_in_progress"
    },
    {
      "at": "2026-04-14T17:48:05.540007+00:00",
      "current_stage": "swarm",
      "message": "Synthesis launch check is still waiting for researcher sidecars",
      "status": "pipeline_in_progress"
    },
    {
      "at": "2026-04-14T17:48:05.909254+00:00",
      "current_stage": "swarm",
      "message": "Synthesis launch check is still waiting for researcher sidecars",
      "status": "pipeline_in_progress"
    },
    {
      "at": "2026-04-14T17:48:10.093015+00:00",
      "current_stage": "synthesis",
      "message": "Swarm stage reconciled",
      "status": "pipeline_in_progress"
    },
    {
      "at": "2026-04-14T17:48:10.950665+00:00",
      "current_stage": "swarm",
      "message": "Synthesis launch check is still waiting for researcher sidecars",
      "status": "pipeline_in_progress"
    },
    {
      "at": "2026-04-14T17:48:11.355523+00:00",
      "current_stage": "swarm",
      "message": "Synthesis launch check is still waiting for researcher sidecars",
      "status": "pipeline_in_progress"
    },
    {
      "at": "2026-04-14T17:48:26.792815+00:00",
      "current_stage": "synthesis",
      "message": "Swarm stage reconciled",
      "status": "pipeline_in_progress"
    },
    {
      "at": "2026-04-14T17:48:27.230463+00:00",
      "current_stage": "swarm",
      "message": "Synthesis launch check is still waiting for researcher sidecars",
      "status": "pipeline_in_progress"
    },
    {
      "at": "2026-04-14T17:48:27.590152+00:00",
      "current_stage": "swarm",
      "message": "Synthesis launch check is still waiting for researcher sidecars",
      "status": "pipeline_in_progress"
    },
    {
      "at": "2026-04-14T17:48:42.960217+00:00",
      "current_stage": "synthesis",
      "message": "Swarm stage reconciled",
      "status": "pipeline_in_progress"
    },
    {
      "at": "2026-04-14T17:48:43.233012+00:00",
      "current_stage": "synthesis",
      "launch_reason": "already_running",
      "message": "Synthesis launch is already in progress",
      "status": "pipeline_in_progress"
    },
    {
      "at": "2026-04-14T17:48:43.578886+00:00",
      "current_stage": "synthesis",
      "launch_reason": "already_running",
      "message": "Synthesis launch is already in progress",
      "status": "pipeline_in_progress"
    },
    {
      "at": "2026-04-14T17:48:58.970526+00:00",
      "current_stage": "synthesis",
      "message": "Swarm stage reconciled",
      "status": "pipeline_in_progress"
    },
    {
      "at": "2026-04-14T17:48:59.196493+00:00",
      "current_stage": "synthesis",
      "launch_reason": "already_running",
      "message": "Synthesis launch is already in progress",
      "status": "pipeline_in_progress"
    },
    {
      "at": "2026-04-14T17:48:59.402030+00:00",
      "current_stage": "synthesis",
      "launch_reason": "already_running",
      "message": "Synthesis launch is already in progress",
      "status": "pipeline_in_progress"
    },
    {
      "at": "2026-04-14T17:49:06.386083+00:00",
      "current_stage": "synthesis",
      "message": "Swarm stage reconciled",
      "status": "pipeline_in_progress"
    },
    {
      "at": "2026-04-14T17:49:06.622831+00:00",
      "current_stage": "synthesis",
      "launch_reason": "already_running",
      "message": "Synthesis launch is already in progress",
      "status": "pipeline_in_progress"
    },
    {
      "at": "2026-04-14T17:49:06.841508+00:00",
      "current_stage": "synthesis",
      "launch_reason": "already_running",
      "message": "Synthesis launch is already in progress",
      "status": "pipeline_in_progress"
    },
    {
      "at": "2026-04-14T17:49:14.772639+00:00",
      "current_stage": "synthesis",
      "message": "Swarm stage reconciled",
      "status": "pipeline_in_progress"
    },
    {
      "at": "2026-04-14T17:49:14.998242+00:00",
      "current_stage": "synthesis",
      "launch_reason": "already_running",
      "message": "Synthesis launch is already in progress",
      "status": "pipeline_in_progress"
    },
    {
      "at": "2026-04-14T17:49:15.198420+00:00",
      "current_stage": "synthesis",
      "launch_reason": "already_running",
      "message": "Synthesis launch is already in progress",
      "status": "pipeline_in_progress"
    },
    {
      "at": "2026-04-14T17:49:30.566720+00:00",
      "current_stage": "synthesis",
      "message": "Swarm stage reconciled",
      "status": "pipeline_in_progress"
    },
    {
      "at": "2026-04-14T17:49:30.769182+00:00",
      "current_stage": "synthesis",
      "launch_reason": "already_running",
      "message": "Synthesis launch is already in progress",
      "status": "pipeline_in_progress"
    },
    {
      "at": "2026-04-14T17:49:30.949173+00:00",
      "current_stage": "synthesis",
      "launch_reason": "already_running",
      "message": "Synthesis launch is already in progress",
      "status": "pipeline_in_progress"
    },
    {
      "at": "2026-04-14T17:49:46.375118+00:00",
      "current_stage": "synthesis",
      "message": "Swarm stage reconciled",
      "status": "pipeline_in_progress"
    },
    {
      "at": "2026-04-14T17:49:46.608259+00:00",
      "current_stage": "synthesis",
      "launch_reason": "already_running",
      "message": "Synthesis launch is already in progress",
      "status": "pipeline_in_progress"
    },
    {
      "at": "2026-04-14T17:49:46.797256+00:00",
      "current_stage": "synthesis",
      "launch_reason": "already_running",
      "message": "Synthesis launch is already in progress",
      "status": "pipeline_in_progress"
    },
    {
      "at": "2026-04-14T17:50:02.148809+00:00",
      "current_stage": "synthesis",
      "message": "Swarm stage reconciled",
      "status": "pipeline_in_progress"
    },
    {
      "at": "2026-04-14T17:50:02.370920+00:00",
      "current_stage": "synthesis",
      "launch_reason": "already_running",
      "message": "Synthesis launch is already in progress",
      "status": "pipeline_in_progress"
    },
    {
      "at": "2026-04-14T17:50:02.575369+00:00",
      "current_stage": "synthesis",
      "launch_reason": "already_running",
      "message": "Synthesis launch is already in progress",
      "status": "pipeline_in_progress"
    },
    {
      "at": "2026-04-14T17:50:07.207891+00:00",
      "current_stage": "synthesis",
      "message": "Swarm stage reconciled",
      "status": "pipeline_in_progress"
    },
    {
      "at": "2026-04-14T17:50:07.482232+00:00",
      "current_stage": "synthesis",
      "launch_reason": "already_running",
      "message": "Synthesis launch is already in progress",
      "status": "pipeline_in_progress"
    },
    {
      "at": "2026-04-14T17:50:07.655929+00:00",
      "current_stage": "synthesis",
      "launch_reason": "already_running",
      "message": "Synthesis launch is already in progress",
      "status": "pipeline_in_progress"
    },
    {
      "at": "2026-04-14T17:50:13.242256+00:00",
      "current_stage": "synthesis",
      "message": "Synthesis completed and decision handoff is ready",
      "status": "pipeline_in_progress"
    },
    {
      "at": "2026-04-14T17:50:17.948914+00:00",
      "current_stage": "decision",
      "message": "Swarm stage reconciled",
      "status": "pipeline_in_progress"
    },
    {
      "at": "2026-04-14T17:50:19.511030+00:00",
      "current_stage": "decision",
      "message": "Decision-Maker launch claimed and worker subprocess started",
      "recovered_stale_claim": false,
      "status": "pipeline_in_progress"
    },
    {
      "at": "2026-04-14T17:50:25.654215+00:00",
      "current_stage": "decision",
      "message": "Decision-Maker stage started",
      "status": "pipeline_in_progress"
    },
    {
      "at": "2026-04-14T17:50:35.517093+00:00",
      "current_stage": "decision",
      "message": "Swarm stage reconciled",
      "status": "pipeline_in_progress"
    },
    {
      "at": "2026-04-14T17:50:50.973387+00:00",
      "current_stage": "decision",
      "message": "Swarm stage reconciled",
      "status": "pipeline_in_progress"
    },
    {
      "at": "2026-04-14T17:51:05.300460+00:00",
      "current_stage": "decision",
      "message": "Decision-Maker completed and packet rendered",
      "status": "pipeline_completed"
    }
  ],
  "updated_at": "2026-04-14T17:51:05.300460+00:00"
}
