{
  "artifact_type": "case_pipeline_status",
  "case_key": "case-20260415-3d3080df",
  "completed_at": "2026-04-15T00:32:46.184525+00:00",
  "current_stage": "decision",
  "dispatch_id": "dispatch-case-20260415-3d3080df-20260415T002239Z",
  "helper_status": {
    "materialize_case_swarm_artifacts": {
      "attempted_at": "2026-04-15T00:32:46.342835+00:00",
      "helper": "materialize_case_swarm_artifacts",
      "ok": true,
      "payload": {
        "artifact_index": "qualitative-db/40-research/cases/case-20260415-3d3080df/artifacts/index.json",
        "case_key": "case-20260415-3d3080df",
        "dispatch_dir": "qualitative-db/40-research/cases/case-20260415-3d3080df/researcher-analyses/2026-04-15/dispatch-case-20260415-3d3080df-20260415T002239Z",
        "ok": true,
        "researcher_swarm_current": "qualitative-db/40-research/cases/case-20260415-3d3080df/researcher-swarm-current.md",
        "researcher_swarm_summary": "qualitative-db/40-research/cases/case-20260415-3d3080df/researcher-swarm-summary.md"
      },
      "returncode": 0
    },
    "post_case_terminal_topic_marker": {
      "attempted_at": "2026-04-15T00:32:42.997684+00:00",
      "helper": "post_case_terminal_topic_marker",
      "ok": true,
      "payload": {
        "case_key": "case-20260415-3d3080df",
        "dispatch_id": "dispatch-case-20260415-3d3080df-20260415T002239Z",
        "noop": true,
        "ok": true,
        "reason": "missing_topic_binding"
      },
      "returncode": 0
    }
  },
  "last_event": {
    "at": "2026-04-15T00:32:46.184525+00:00",
    "current_stage": "decision",
    "message": "Decision-Maker completed and packet rendered",
    "status": "pipeline_completed"
  },
  "market_id": "551a0230-0ffb-42cc-9103-4bea5dc0cb4e",
  "market_title": "Will the price of Bitcoin be above $70,000 on April 20?",
  "runner_id": "run_decision_maker",
  "schema_version": "case-pipeline-status/v1",
  "stage_detail_states": {
    "decision": "completed",
    "dispatch": "completed",
    "swarm": "completed",
    "synthesis": "completed"
  },
  "stage_statuses": {
    "decision": "completed",
    "dispatch": "completed",
    "swarm": "completed",
    "synthesis": "completed"
  },
  "started_at": "2026-04-15T00:24:18.731642+00:00",
  "status": "pipeline_completed",
  "terminal_summary": {
    "decision_handoff_path": "qualitative-db/40-research/cases/case-20260415-3d3080df/researcher-analyses/2026-04-15/dispatch-case-20260415-3d3080df-20260415T002239Z/decision-handoff.md",
    "decision_packet_json": "qualitative-db/40-research/cases/case-20260415-3d3080df/decision-maker/artifacts/decision-maker-packet.json",
    "decision_packet_markdown": "qualitative-db/40-research/cases/case-20260415-3d3080df/decision-maker/decision-maker-packet.md",
    "decision_parse_attempt_count": 1,
    "decision_readiness": "ready",
    "decision_recovered_after_retry": false,
    "forecast_decision_persist_error": "",
    "forecast_decision_persisted": true,
    "position_policy": "hold_only",
    "raw_gateway_response_path": "roles/decision-maker/runtime/artifacts/case-20260415-3d3080df/decision-gateway-response-dispatch-case-20260415-3d3080df-20260415T002239Z.json",
    "raw_response_text_path": "roles/decision-maker/runtime/artifacts/case-20260415-3d3080df/decision-response-dispatch-case-20260415-3d3080df-20260415T002239Z.raw.txt",
    "recommended_side": "yes",
    "swarm_stage_status_path": "qualitative-db/40-research/cases/case-20260415-3d3080df/researcher-analyses/2026-04-15/dispatch-case-20260415-3d3080df-20260415T002239Z/swarm-stage-status.json",
    "synthesis_artifact_path": "qualitative-db/40-research/cases/case-20260415-3d3080df/researcher-analyses/2026-04-15/dispatch-case-20260415-3d3080df-20260415T002239Z/syndicated-finding.md",
    "trade_authorization": "watch_only"
  },
  "timeline": [
    {
      "at": "2026-04-15T00:24:18.731642+00:00",
      "current_stage": "swarm",
      "manifest_path": "/Users/agent2/.openclaw/orchestrator/roles/orchestrator/researchers-swarm-subagents/runtime/dispatch-manifests/dispatch-case-20260415-3d3080df-20260415T002239Z.json",
      "message": "Fresh case claimed and dispatch launched",
      "status": "pipeline_started",
      "target_session_key": ""
    },
    {
      "at": "2026-04-15T00:24:19.168041+00:00",
      "current_stage": "swarm",
      "message": "Swarm stage reconciled",
      "status": "pipeline_in_progress"
    },
    {
      "at": "2026-04-15T00:24:31.364582+00:00",
      "current_stage": "swarm",
      "message": "Swarm stage reconciled",
      "status": "pipeline_in_progress"
    },
    {
      "at": "2026-04-15T00:24:34.891422+00:00",
      "current_stage": "swarm",
      "message": "Swarm stage reconciled",
      "status": "pipeline_in_progress"
    },
    {
      "at": "2026-04-15T00:24:50.412444+00:00",
      "current_stage": "swarm",
      "message": "Swarm stage reconciled",
      "status": "pipeline_in_progress"
    },
    {
      "at": "2026-04-15T00:25:05.942236+00:00",
      "current_stage": "swarm",
      "message": "Swarm stage reconciled",
      "status": "pipeline_in_progress"
    },
    {
      "at": "2026-04-15T00:25:21.481028+00:00",
      "current_stage": "swarm",
      "message": "Swarm stage reconciled",
      "status": "pipeline_in_progress"
    },
    {
      "at": "2026-04-15T00:25:31.930826+00:00",
      "current_stage": "swarm",
      "message": "Swarm stage reconciled",
      "status": "pipeline_in_progress"
    },
    {
      "at": "2026-04-15T00:25:36.997329+00:00",
      "current_stage": "swarm",
      "message": "Swarm stage reconciled",
      "status": "pipeline_in_progress"
    },
    {
      "at": "2026-04-15T00:25:52.525216+00:00",
      "current_stage": "swarm",
      "message": "Swarm stage reconciled",
      "status": "pipeline_in_progress"
    },
    {
      "at": "2026-04-15T00:26:08.066198+00:00",
      "current_stage": "swarm",
      "message": "Swarm stage reconciled",
      "status": "pipeline_in_progress"
    },
    {
      "at": "2026-04-15T00:26:23.608065+00:00",
      "current_stage": "swarm",
      "message": "Swarm stage reconciled",
      "status": "pipeline_in_progress"
    },
    {
      "at": "2026-04-15T00:26:32.471917+00:00",
      "current_stage": "swarm",
      "message": "Swarm stage reconciled",
      "status": "pipeline_in_progress"
    },
    {
      "at": "2026-04-15T00:26:39.136676+00:00",
      "current_stage": "swarm",
      "message": "Swarm stage reconciled",
      "status": "pipeline_in_progress"
    },
    {
      "at": "2026-04-15T00:26:54.653543+00:00",
      "current_stage": "swarm",
      "message": "Swarm stage reconciled",
      "status": "pipeline_in_progress"
    },
    {
      "at": "2026-04-15T00:27:10.199119+00:00",
      "current_stage": "swarm",
      "message": "Swarm stage reconciled",
      "status": "pipeline_in_progress"
    },
    {
      "at": "2026-04-15T00:27:25.691608+00:00",
      "current_stage": "swarm",
      "message": "Swarm stage reconciled",
      "status": "pipeline_in_progress"
    },
    {
      "at": "2026-04-15T00:27:33.008430+00:00",
      "current_stage": "swarm",
      "message": "Swarm stage reconciled",
      "status": "pipeline_in_progress"
    },
    {
      "at": "2026-04-15T00:27:41.226456+00:00",
      "current_stage": "swarm",
      "message": "Swarm stage reconciled",
      "status": "pipeline_in_progress"
    },
    {
      "at": "2026-04-15T00:27:56.753218+00:00",
      "current_stage": "swarm",
      "message": "Swarm stage reconciled",
      "status": "pipeline_in_progress"
    },
    {
      "at": "2026-04-15T00:28:12.246133+00:00",
      "current_stage": "swarm",
      "message": "Swarm stage reconciled",
      "status": "pipeline_in_progress"
    },
    {
      "at": "2026-04-15T00:28:27.758920+00:00",
      "current_stage": "swarm",
      "message": "Swarm stage reconciled",
      "status": "pipeline_in_progress"
    },
    {
      "at": "2026-04-15T00:28:33.553187+00:00",
      "current_stage": "swarm",
      "message": "Swarm stage reconciled",
      "status": "pipeline_in_progress"
    },
    {
      "at": "2026-04-15T00:28:43.289801+00:00",
      "current_stage": "swarm",
      "message": "Swarm stage reconciled",
      "status": "pipeline_in_progress"
    },
    {
      "at": "2026-04-15T00:28:58.831192+00:00",
      "current_stage": "swarm",
      "message": "Swarm stage reconciled",
      "status": "pipeline_in_progress"
    },
    {
      "at": "2026-04-15T00:29:14.278259+00:00",
      "current_stage": "swarm",
      "message": "Swarm stage reconciled",
      "status": "pipeline_in_progress"
    },
    {
      "at": "2026-04-15T00:29:29.816209+00:00",
      "current_stage": "synthesis",
      "message": "Swarm stage reconciled",
      "status": "pipeline_in_progress"
    },
    {
      "at": "2026-04-15T00:29:30.589816+00:00",
      "current_stage": "swarm",
      "message": "Synthesis launch check is still waiting for researcher sidecars",
      "status": "pipeline_in_progress"
    },
    {
      "at": "2026-04-15T00:29:30.954383+00:00",
      "current_stage": "swarm",
      "message": "Synthesis launch check is still waiting for researcher sidecars",
      "status": "pipeline_in_progress"
    },
    {
      "at": "2026-04-15T00:29:34.093025+00:00",
      "current_stage": "synthesis",
      "message": "Swarm stage reconciled",
      "status": "pipeline_in_progress"
    },
    {
      "at": "2026-04-15T00:29:34.485985+00:00",
      "current_stage": "swarm",
      "message": "Synthesis launch check is still waiting for researcher sidecars",
      "status": "pipeline_in_progress"
    },
    {
      "at": "2026-04-15T00:29:34.853968+00:00",
      "current_stage": "swarm",
      "message": "Synthesis launch check is still waiting for researcher sidecars",
      "status": "pipeline_in_progress"
    },
    {
      "at": "2026-04-15T00:29:46.469816+00:00",
      "current_stage": "synthesis",
      "message": "Swarm stage reconciled",
      "status": "pipeline_in_progress"
    },
    {
      "at": "2026-04-15T00:29:46.863788+00:00",
      "current_stage": "swarm",
      "message": "Synthesis launch check is still waiting for researcher sidecars",
      "status": "pipeline_in_progress"
    },
    {
      "at": "2026-04-15T00:29:47.234100+00:00",
      "current_stage": "swarm",
      "message": "Synthesis launch check is still waiting for researcher sidecars",
      "status": "pipeline_in_progress"
    },
    {
      "at": "2026-04-15T00:30:02.694748+00:00",
      "current_stage": "synthesis",
      "message": "Swarm stage reconciled",
      "status": "pipeline_in_progress"
    },
    {
      "at": "2026-04-15T00:30:03.064438+00:00",
      "current_stage": "synthesis",
      "launch_reason": "already_running",
      "message": "Synthesis launch is already in progress",
      "status": "pipeline_in_progress"
    },
    {
      "at": "2026-04-15T00:30:03.407993+00:00",
      "current_stage": "synthesis",
      "launch_reason": "already_running",
      "message": "Synthesis launch is already in progress",
      "status": "pipeline_in_progress"
    },
    {
      "at": "2026-04-15T00:30:18.893266+00:00",
      "current_stage": "synthesis",
      "message": "Swarm stage reconciled",
      "status": "pipeline_in_progress"
    },
    {
      "at": "2026-04-15T00:30:19.102707+00:00",
      "current_stage": "synthesis",
      "launch_reason": "already_running",
      "message": "Synthesis launch is already in progress",
      "status": "pipeline_in_progress"
    },
    {
      "at": "2026-04-15T00:30:19.276521+00:00",
      "current_stage": "synthesis",
      "launch_reason": "already_running",
      "message": "Synthesis launch is already in progress",
      "status": "pipeline_in_progress"
    },
    {
      "at": "2026-04-15T00:30:34.748817+00:00",
      "current_stage": "synthesis",
      "message": "Swarm stage reconciled",
      "status": "pipeline_in_progress"
    },
    {
      "at": "2026-04-15T00:30:34.978037+00:00",
      "current_stage": "synthesis",
      "launch_reason": "already_running",
      "message": "Synthesis launch is already in progress",
      "status": "pipeline_in_progress"
    },
    {
      "at": "2026-04-15T00:30:35.157642+00:00",
      "current_stage": "synthesis",
      "launch_reason": "already_running",
      "message": "Synthesis launch is already in progress",
      "status": "pipeline_in_progress"
    },
    {
      "at": "2026-04-15T00:30:35.389410+00:00",
      "current_stage": "synthesis",
      "message": "Swarm stage reconciled",
      "status": "pipeline_in_progress"
    },
    {
      "at": "2026-04-15T00:30:35.604541+00:00",
      "current_stage": "synthesis",
      "launch_reason": "already_running",
      "message": "Synthesis launch is already in progress",
      "status": "pipeline_in_progress"
    },
    {
      "at": "2026-04-15T00:30:35.801157+00:00",
      "current_stage": "synthesis",
      "launch_reason": "already_running",
      "message": "Synthesis launch is already in progress",
      "status": "pipeline_in_progress"
    },
    {
      "at": "2026-04-15T00:30:50.651048+00:00",
      "current_stage": "synthesis",
      "message": "Swarm stage reconciled",
      "status": "pipeline_in_progress"
    },
    {
      "at": "2026-04-15T00:30:50.910209+00:00",
      "current_stage": "synthesis",
      "launch_reason": "already_running",
      "message": "Synthesis launch is already in progress",
      "status": "pipeline_in_progress"
    },
    {
      "at": "2026-04-15T00:30:51.136171+00:00",
      "current_stage": "synthesis",
      "launch_reason": "already_running",
      "message": "Synthesis launch is already in progress",
      "status": "pipeline_in_progress"
    },
    {
      "at": "2026-04-15T00:31:06.483494+00:00",
      "current_stage": "synthesis",
      "message": "Swarm stage reconciled",
      "status": "pipeline_in_progress"
    },
    {
      "at": "2026-04-15T00:31:06.720588+00:00",
      "current_stage": "synthesis",
      "launch_reason": "already_running",
      "message": "Synthesis launch is already in progress",
      "status": "pipeline_in_progress"
    },
    {
      "at": "2026-04-15T00:31:06.939107+00:00",
      "current_stage": "synthesis",
      "launch_reason": "already_running",
      "message": "Synthesis launch is already in progress",
      "status": "pipeline_in_progress"
    },
    {
      "at": "2026-04-15T00:31:22.360741+00:00",
      "current_stage": "synthesis",
      "message": "Swarm stage reconciled",
      "status": "pipeline_in_progress"
    },
    {
      "at": "2026-04-15T00:31:22.571957+00:00",
      "current_stage": "synthesis",
      "launch_reason": "already_running",
      "message": "Synthesis launch is already in progress",
      "status": "pipeline_in_progress"
    },
    {
      "at": "2026-04-15T00:31:22.754069+00:00",
      "current_stage": "synthesis",
      "launch_reason": "already_running",
      "message": "Synthesis launch is already in progress",
      "status": "pipeline_in_progress"
    },
    {
      "at": "2026-04-15T00:31:36.347365+00:00",
      "current_stage": "synthesis",
      "message": "Swarm stage reconciled",
      "status": "pipeline_in_progress"
    },
    {
      "at": "2026-04-15T00:31:36.569331+00:00",
      "current_stage": "synthesis",
      "launch_reason": "already_running",
      "message": "Synthesis launch is already in progress",
      "status": "pipeline_in_progress"
    },
    {
      "at": "2026-04-15T00:31:36.776542+00:00",
      "current_stage": "synthesis",
      "launch_reason": "already_running",
      "message": "Synthesis launch is already in progress",
      "status": "pipeline_in_progress"
    },
    {
      "at": "2026-04-15T00:31:38.102849+00:00",
      "current_stage": "synthesis",
      "message": "Swarm stage reconciled",
      "status": "pipeline_in_progress"
    },
    {
      "at": "2026-04-15T00:31:38.334462+00:00",
      "current_stage": "synthesis",
      "launch_reason": "already_running",
      "message": "Synthesis launch is already in progress",
      "status": "pipeline_in_progress"
    },
    {
      "at": "2026-04-15T00:31:38.541292+00:00",
      "current_stage": "synthesis",
      "launch_reason": "already_running",
      "message": "Synthesis launch is already in progress",
      "status": "pipeline_in_progress"
    },
    {
      "at": "2026-04-15T00:31:42.447752+00:00",
      "current_stage": "synthesis",
      "message": "Synthesis completed and decision handoff is ready",
      "status": "pipeline_in_progress"
    },
    {
      "at": "2026-04-15T00:31:53.956557+00:00",
      "current_stage": "decision",
      "message": "Swarm stage reconciled",
      "status": "pipeline_in_progress"
    },
    {
      "at": "2026-04-15T00:31:55.538435+00:00",
      "current_stage": "decision",
      "message": "Decision-Maker launch claimed and worker subprocess started",
      "recovered_stale_claim": false,
      "status": "pipeline_in_progress"
    },
    {
      "at": "2026-04-15T00:32:01.761638+00:00",
      "current_stage": "decision",
      "message": "Decision-Maker stage started",
      "status": "pipeline_in_progress"
    },
    {
      "at": "2026-04-15T00:32:11.551634+00:00",
      "current_stage": "decision",
      "message": "Swarm stage reconciled",
      "status": "pipeline_in_progress"
    },
    {
      "at": "2026-04-15T00:32:26.974171+00:00",
      "current_stage": "decision",
      "message": "Swarm stage reconciled",
      "status": "pipeline_in_progress"
    },
    {
      "at": "2026-04-15T00:32:37.145596+00:00",
      "current_stage": "decision",
      "message": "Swarm stage reconciled",
      "status": "pipeline_in_progress"
    },
    {
      "at": "2026-04-15T00:32:42.437233+00:00",
      "current_stage": "decision",
      "message": "Swarm stage reconciled",
      "status": "pipeline_in_progress"
    },
    {
      "at": "2026-04-15T00:32:42.627173+00:00",
      "current_stage": "decision",
      "message": "Watchdog finalized pipeline from ready decision artifacts",
      "status": "pipeline_completed"
    },
    {
      "at": "2026-04-15T00:32:46.184525+00:00",
      "current_stage": "decision",
      "message": "Decision-Maker completed and packet rendered",
      "status": "pipeline_completed"
    }
  ],
  "updated_at": "2026-04-15T00:32:46.184525+00:00"
}
