{
  "packet_type": "occurrence_backed_mechanism_packet",
  "compiler_version": "2026-04-16-occurrence-v1",
  "proposal_source": "driver_occurrence_compiler",
  "packet_key": "occurrence-packet:station-location-basis-risk",
  "proposal_key": "driver-mechanism:station-location-basis-risk",
  "candidate_type": "packet",
  "candidate_slug": "station-location-basis-risk",
  "candidate_label": "station-location-basis-risk",
  "normalized_family": "station-location-basis-risk",
  "family_assignment_source": "generated_index",
  "candidate_note_path": "candidate-notes/generated-driver-candidate-station-location-basis-risk.md",
  "source_lane": "public.proposed_driver_occurrences",
  "routing": {
    "mode": "packet_only",
    "shadow_eligible": false,
    "trial_eligible": false,
    "promotion_eligible": false,
    "next_step": "materialize_provisional_families"
  },
  "source_summary": {
    "source_occurrence_count": 2,
    "distinct_case_count": 1,
    "distinct_persona_count": 1,
    "distinct_dispatch_count": 1,
    "source_mix": {
      "db": 2
    },
    "artifact_kind_counts": {
      "assumption": 1,
      "persona": 1
    },
    "difficulty_classes": [
      "low"
    ],
    "source_of_truth_classes": [
      "multi_source_ambiguous"
    ],
    "first_observed_at": "2026-04-16T06:20:27.100221-04:00",
    "last_observed_at": "2026-04-16T06:20:27.143682-04:00"
  },
  "support": {
    "case_keys": [
      "case-20260416-bacb47cd"
    ],
    "personas": [
      "base-rate"
    ],
    "dispatch_ids": [
      "dispatch-case-20260416-bacb47cd-20260416T101708Z"
    ],
    "related_entities": [],
    "related_canonical_drivers": [],
    "canonical_driver_suggestions": [],
    "top_related_entities": [],
    "top_related_canonical_drivers": [],
    "top_canonical_driver_suggestions": []
  },
  "seed_hints": {
    "node_seed": {
      "candidate_key": "station-location-basis-risk",
      "candidate_label": "station-location-basis-risk",
      "mechanism_family": "station-location-basis-risk",
      "status": "shadow_only_provisional_seed"
    },
    "edge_seeds": []
  },
  "compiler_metadata": {
    "generated_index_present": true,
    "hint_source_path": "qualitative-db/40-research/review-queue/drivers-candidates/generated-index.json",
    "hint_canon_coverage_status": "novel",
    "hint_canon_coverage_driver": "",
    "hint_occurrence_count": 2,
    "hint_distinct_case_count": 1,
    "hint_distinct_persona_count": 1,
    "occurrence_paths": [
      "qualitative-db/40-research/cases/case-20260416-bacb47cd/researcher-analyses/2026-04-16/dispatch-case-20260416-bacb47cd-20260416T101708Z/assumptions/base-rate.md",
      "qualitative-db/40-research/cases/case-20260416-bacb47cd/researcher-analyses/2026-04-16/dispatch-case-20260416-bacb47cd-20260416T101708Z/personas/base-rate.md"
    ]
  },
  "source_occurrences": [
    {
      "artifact_path": "qualitative-db/40-research/cases/case-20260416-bacb47cd/researcher-analyses/2026-04-16/dispatch-case-20260416-bacb47cd-20260416T101708Z/assumptions/base-rate.md",
      "proposed_driver_label": "station-location-basis-risk",
      "proposed_driver_slug": "station-location-basis-risk",
      "case_key": "case-20260416-bacb47cd",
      "dispatch_id": "dispatch-case-20260416-bacb47cd-20260416T101708Z",
      "research_run_id": "0c338125-dc6d-434f-85e5-b84e0ad3c09d",
      "persona": "base-rate",
      "artifact_kind": "assumption",
      "related_entities": [],
      "related_canonical_drivers": [],
      "canonical_driver_suggestions": [],
      "difficulty_class": "low",
      "source_of_truth_class": "multi_source_ambiguous",
      "occurred_at": "2026-04-16T06:20:27.143682-04:00",
      "status": "active"
    },
    {
      "artifact_path": "qualitative-db/40-research/cases/case-20260416-bacb47cd/researcher-analyses/2026-04-16/dispatch-case-20260416-bacb47cd-20260416T101708Z/personas/base-rate.md",
      "proposed_driver_label": "station-location-basis-risk",
      "proposed_driver_slug": "station-location-basis-risk",
      "case_key": "case-20260416-bacb47cd",
      "dispatch_id": "dispatch-case-20260416-bacb47cd-20260416T101708Z",
      "research_run_id": "0c338125-dc6d-434f-85e5-b84e0ad3c09d",
      "persona": "base-rate",
      "artifact_kind": "persona",
      "related_entities": [],
      "related_canonical_drivers": [],
      "canonical_driver_suggestions": [],
      "difficulty_class": "low",
      "source_of_truth_class": "multi_source_ambiguous",
      "occurred_at": "2026-04-16T06:20:27.100221-04:00",
      "status": "active"
    }
  ],
  "packet_hash": "df4b592a1b26e905fdd3e847d9c77d9f00aab62cb7b23b4dc406204c07564dfe"
}
