{
  "artifact_type": "causal_node",
  "schema_version": "v1",
  "node_key": "publication-window-timing",
  "contexts": {
    "question_mechanics": [
      "publication-timing",
      "scheduled-publication"
    ],
    "categories": [
      "macro",
      "entertainment",
      "politics"
    ]
  },
  "linked_paths": {
    "drivers": [],
    "domains": [],
    "entities": []
  },
  "mechanism_family": "publication_timing",
  "source_kind": "seed",
  "lifecycle_stage": "draft",
  "superseded_by_key": ""
}
