{
  "artifact_type": "swarm_stage_status",
  "case_key": "case-20260413-7b99a566",
  "check_only": false,
  "completed_assumptions": [],
  "completed_evidence": [
    "risk-manager"
  ],
  "completed_personas": [
    "catalyst-hunter"
  ],
  "dispatch_dir": "qualitative-db/40-research/cases/case-20260413-7b99a566/researcher-analyses/2026-04-13/dispatch-case-20260413T140531Z",
  "dispatch_id": "dispatch-case-20260413T140531Z",
  "expected_personas": [
    "base-rate",
    "catalyst-hunter",
    "market-implied",
    "risk-manager",
    "variant-view"
  ],
  "generated_at": "2026-04-13T14:13:47.019548+00:00",
  "health": "in_progress",
  "latest_update_seconds_ago": 35.696025133132935,
  "manifest_path": "",
  "missing_personas": [
    "base-rate",
    "market-implied",
    "risk-manager",
    "variant-view"
  ],
  "recommendation": "swarm is still progressing or recently updated",
  "recommended_resume_command": "python3 roles/orchestrator/researchers-swarm-subagents/runtime/scripts/resume_swarm_stage.py --case-key case-20260413-7b99a566 --pretty",
  "schema_version": "swarm-stage-status/v1",
  "stale_seconds_threshold": 900.0,
  "status": "in_progress",
  "status_file_path": "qualitative-db/40-research/cases/case-20260413-7b99a566/researcher-analyses/2026-04-13/dispatch-case-20260413T140531Z/swarm-stage-status.json",
  "summary_exists": false,
  "synthesis_status": "",
  "synthesis_status_path": ""
}
