{
  "type": "occurrence_compiler_status",
  "ok": true,
  "run_id": "occurrence-compiler-2026-04-16T23:19:11Z",
  "generated_at": "2026-04-16T23:19:11Z",
  "compiler_version": "2026-04-16-occurrence-v1",
  "proposal_source": "driver_occurrence_compiler",
  "source_lane": "public.proposed_driver_occurrences",
  "driver_index_path": "qualitative-db/40-research/review-queue/drivers-candidates/generated-index.json",
  "packet_root": "qualitative-db/60-causal-map/generated/occurrence-compiler/packets",
  "source_occurrence_count": 782,
  "candidate_count": 267,
  "family_count": 112,
  "db_occurrence_count": 782,
  "markdown_fallback_occurrence_count": 13,
  "generated_index_present": true,
  "generated_index_candidate_count": 267,
  "generated_index_family_count": 112,
  "fallback_family_assignment_count": 0,
  "top_families": [
    {
      "family_key": "resolution-mechanics",
      "candidate_count": 119,
      "source_occurrence_count": 398,
      "distinct_case_count": 84,
      "distinct_persona_count": 5,
      "assignment_source_mix": {
        "generated_index": 119
      }
    },
    {
      "family_key": "publication-timing",
      "candidate_count": 19,
      "source_occurrence_count": 67,
      "distinct_case_count": 23,
      "distinct_persona_count": 5,
      "assignment_source_mix": {
        "generated_index": 19
      }
    },
    {
      "family_key": "release-window-demand",
      "candidate_count": 17,
      "source_occurrence_count": 45,
      "distinct_case_count": 14,
      "distinct_persona_count": 5,
      "assignment_source_mix": {
        "generated_index": 17
      }
    },
    {
      "family_key": "resolution-mapping",
      "candidate_count": 4,
      "source_occurrence_count": 10,
      "distinct_case_count": 3,
      "distinct_persona_count": 3,
      "assignment_source_mix": {
        "generated_index": 4
      }
    },
    {
      "family_key": "team-strength-gap",
      "candidate_count": 1,
      "source_occurrence_count": 7,
      "distinct_case_count": 3,
      "distinct_persona_count": 2,
      "assignment_source_mix": {
        "generated_index": 1
      }
    },
    {
      "family_key": "home-field-advantage",
      "candidate_count": 1,
      "source_occurrence_count": 6,
      "distinct_case_count": 3,
      "distinct_persona_count": 2,
      "assignment_source_mix": {
        "generated_index": 1
      }
    },
    {
      "family_key": "residual-path-volatility",
      "candidate_count": 1,
      "source_occurrence_count": 6,
      "distinct_case_count": 1,
      "distinct_persona_count": 2,
      "assignment_source_mix": {
        "generated_index": 1
      }
    },
    {
      "family_key": "alliance-cohesion",
      "candidate_count": 1,
      "source_occurrence_count": 3,
      "distinct_case_count": 1,
      "distinct_persona_count": 1,
      "assignment_source_mix": {
        "generated_index": 1
      }
    },
    {
      "family_key": "anti-incumbency",
      "candidate_count": 1,
      "source_occurrence_count": 3,
      "distinct_case_count": 1,
      "distinct_persona_count": 1,
      "assignment_source_mix": {
        "generated_index": 1
      }
    },
    {
      "family_key": "bicameral-coordination-risk",
      "candidate_count": 1,
      "source_occurrence_count": 3,
      "distinct_case_count": 1,
      "distinct_persona_count": 1,
      "assignment_source_mix": {
        "generated_index": 1
      }
    },
    {
      "family_key": "binance-1m-high-governing-surface-equivalence",
      "candidate_count": 1,
      "source_occurrence_count": 3,
      "distinct_case_count": 1,
      "distinct_persona_count": 1,
      "assignment_source_mix": {
        "generated_index": 1
      }
    },
    {
      "family_key": "binance-1m-touch-market-microstructure",
      "candidate_count": 1,
      "source_occurrence_count": 3,
      "distinct_case_count": 1,
      "distinct_persona_count": 1,
      "assignment_source_mix": {
        "generated_index": 1
      }
    }
  ],
  "top_packets": [
    {
      "packet_key": "occurrence-packet:threshold-proximity",
      "candidate_slug": "threshold-proximity",
      "candidate_label": "threshold-proximity",
      "normalized_family": "resolution-mechanics",
      "packet_path": "qualitative-db/60-causal-map/generated/occurrence-compiler/packets/threshold-proximity.json",
      "source_occurrence_count": 42,
      "distinct_case_count": 12,
      "distinct_persona_count": 4
    },
    {
      "packet_key": "occurrence-packet:intraday-volatility",
      "candidate_slug": "intraday-volatility",
      "candidate_label": "intraday-volatility",
      "normalized_family": "resolution-mechanics",
      "packet_path": "qualitative-db/60-causal-map/generated/occurrence-compiler/packets/intraday-volatility.json",
      "source_occurrence_count": 27,
      "distinct_case_count": 10,
      "distinct_persona_count": 3
    },
    {
      "packet_key": "occurrence-packet:short-horizon-crypto-volatility",
      "candidate_slug": "short-horizon-crypto-volatility",
      "candidate_label": "short-horizon-crypto-volatility",
      "normalized_family": "resolution-mechanics",
      "packet_path": "qualitative-db/60-causal-map/generated/occurrence-compiler/packets/short-horizon-crypto-volatility.json",
      "source_occurrence_count": 19,
      "distinct_case_count": 8,
      "distinct_persona_count": 4
    },
    {
      "packet_key": "occurrence-packet:macro-event-timing",
      "candidate_slug": "macro-event-timing",
      "candidate_label": "macro-event-timing",
      "normalized_family": "publication-timing",
      "packet_path": "qualitative-db/60-causal-map/generated/occurrence-compiler/packets/macro-event-timing.json",
      "source_occurrence_count": 18,
      "distinct_case_count": 7,
      "distinct_persona_count": 1
    },
    {
      "packet_key": "occurrence-packet:threshold-close-mechanics",
      "candidate_slug": "threshold-close-mechanics",
      "candidate_label": "threshold-close mechanics",
      "normalized_family": "resolution-mechanics",
      "packet_path": "qualitative-db/60-causal-map/generated/occurrence-compiler/packets/threshold-close-mechanics.json",
      "source_occurrence_count": 9,
      "distinct_case_count": 4,
      "distinct_persona_count": 2
    },
    {
      "packet_key": "occurrence-packet:team-strength-gap",
      "candidate_slug": "team-strength-gap",
      "candidate_label": "team-strength-gap",
      "normalized_family": "team-strength-gap",
      "packet_path": "qualitative-db/60-causal-map/generated/occurrence-compiler/packets/team-strength-gap.json",
      "source_occurrence_count": 7,
      "distinct_case_count": 3,
      "distinct_persona_count": 2
    },
    {
      "packet_key": "occurrence-packet:threshold-close-timing-risk",
      "candidate_slug": "threshold-close-timing-risk",
      "candidate_label": "threshold-close timing risk",
      "normalized_family": "publication-timing",
      "packet_path": "qualitative-db/60-causal-map/generated/occurrence-compiler/packets/threshold-close-timing-risk.json",
      "source_occurrence_count": 7,
      "distinct_case_count": 3,
      "distinct_persona_count": 2
    },
    {
      "packet_key": "occurrence-packet:intraday-volatility-window",
      "candidate_slug": "intraday-volatility-window",
      "candidate_label": "intraday-volatility-window",
      "normalized_family": "release-window-demand",
      "packet_path": "qualitative-db/60-causal-map/generated/occurrence-compiler/packets/intraday-volatility-window.json",
      "source_occurrence_count": 7,
      "distinct_case_count": 3,
      "distinct_persona_count": 1
    },
    {
      "packet_key": "occurrence-packet:macro-event-risk",
      "candidate_slug": "macro-event-risk",
      "candidate_label": "macro-event-risk",
      "normalized_family": "resolution-mechanics",
      "packet_path": "qualitative-db/60-causal-map/generated/occurrence-compiler/packets/macro-event-risk.json",
      "source_occurrence_count": 7,
      "distinct_case_count": 3,
      "distinct_persona_count": 1
    },
    {
      "packet_key": "occurrence-packet:home-field-advantage",
      "candidate_slug": "home-field-advantage",
      "candidate_label": "home-field-advantage",
      "normalized_family": "home-field-advantage",
      "packet_path": "qualitative-db/60-causal-map/generated/occurrence-compiler/packets/home-field-advantage.json",
      "source_occurrence_count": 6,
      "distinct_case_count": 3,
      "distinct_persona_count": 2
    },
    {
      "packet_key": "occurrence-packet:short-horizon-threshold-volatility",
      "candidate_slug": "short-horizon-threshold-volatility",
      "candidate_label": "short-horizon-threshold-volatility",
      "normalized_family": "resolution-mechanics",
      "packet_path": "qualitative-db/60-causal-map/generated/occurrence-compiler/packets/short-horizon-threshold-volatility.json",
      "source_occurrence_count": 6,
      "distinct_case_count": 2,
      "distinct_persona_count": 2
    },
    {
      "packet_key": "occurrence-packet:timing-risk",
      "candidate_slug": "timing-risk",
      "candidate_label": "timing-risk",
      "normalized_family": "publication-timing",
      "packet_path": "qualitative-db/60-causal-map/generated/occurrence-compiler/packets/timing-risk.json",
      "source_occurrence_count": 6,
      "distinct_case_count": 2,
      "distinct_persona_count": 1
    },
    {
      "packet_key": "occurrence-packet:residual-path-volatility",
      "candidate_slug": "residual-path-volatility",
      "candidate_label": "residual path volatility",
      "normalized_family": "residual-path-volatility",
      "packet_path": "qualitative-db/60-causal-map/generated/occurrence-compiler/packets/residual-path-volatility.json",
      "source_occurrence_count": 6,
      "distinct_case_count": 1,
      "distinct_persona_count": 2
    },
    {
      "packet_key": "occurrence-packet:touch-style-settlement-mechanics",
      "candidate_slug": "touch-style-settlement-mechanics",
      "candidate_label": "touch-style settlement mechanics",
      "normalized_family": "resolution-mechanics",
      "packet_path": "qualitative-db/60-causal-map/generated/occurrence-compiler/packets/touch-style-settlement-mechanics.json",
      "source_occurrence_count": 6,
      "distinct_case_count": 1,
      "distinct_persona_count": 2
    },
    {
      "packet_key": "occurrence-packet:crypto-price-threshold-resolution",
      "candidate_slug": "crypto-price-threshold-resolution",
      "candidate_label": "crypto-price-threshold-resolution",
      "normalized_family": "resolution-mechanics",
      "packet_path": "qualitative-db/60-causal-map/generated/occurrence-compiler/packets/crypto-price-threshold-resolution.json",
      "source_occurrence_count": 5,
      "distinct_case_count": 2,
      "distinct_persona_count": 2
    },
    {
      "packet_key": "occurrence-packet:intraday-timing-risk",
      "candidate_slug": "intraday-timing-risk",
      "candidate_label": "intraday-timing-risk",
      "normalized_family": "publication-timing",
      "packet_path": "qualitative-db/60-causal-map/generated/occurrence-compiler/packets/intraday-timing-risk.json",
      "source_occurrence_count": 5,
      "distinct_case_count": 2,
      "distinct_persona_count": 1
    },
    {
      "packet_key": "occurrence-packet:scheduled-macro-catalyst-gap",
      "candidate_slug": "scheduled-macro-catalyst-gap",
      "candidate_label": "scheduled-macro-catalyst-gap",
      "normalized_family": "resolution-mechanics",
      "packet_path": "qualitative-db/60-causal-map/generated/occurrence-compiler/packets/scheduled-macro-catalyst-gap.json",
      "source_occurrence_count": 5,
      "distinct_case_count": 2,
      "distinct_persona_count": 1
    },
    {
      "packet_key": "occurrence-packet:contract-interpretation-risk",
      "candidate_slug": "contract-interpretation-risk",
      "candidate_label": "contract-interpretation-risk",
      "normalized_family": "resolution-mechanics",
      "packet_path": "qualitative-db/60-causal-map/generated/occurrence-compiler/packets/contract-interpretation-risk.json",
      "source_occurrence_count": 5,
      "distinct_case_count": 1,
      "distinct_persona_count": 2
    },
    {
      "packet_key": "occurrence-packet:threshold-distance",
      "candidate_slug": "threshold-distance",
      "candidate_label": "threshold-distance",
      "normalized_family": "resolution-mechanics",
      "packet_path": "qualitative-db/60-causal-map/generated/occurrence-compiler/packets/threshold-distance.json",
      "source_occurrence_count": 4,
      "distinct_case_count": 2,
      "distinct_persona_count": 2
    },
    {
      "packet_key": "occurrence-packet:short-horizon-crypto-threshold-touch",
      "candidate_slug": "short-horizon-crypto-threshold-touch",
      "candidate_label": "short-horizon-crypto-threshold-touch",
      "normalized_family": "resolution-mechanics",
      "packet_path": "qualitative-db/60-causal-map/generated/occurrence-compiler/packets/short-horizon-crypto-threshold-touch.json",
      "source_occurrence_count": 4,
      "distinct_case_count": 2,
      "distinct_persona_count": 1
    }
  ],
  "write_outcomes": {
    "packet_json_unchanged": 267,
    "packet_md_unchanged": 267
  },
  "warnings": [],
  "db_summary": {
    "compiled_row_count": 267,
    "family_count": 112,
    "latest_updated_at": "2026-04-16T19:19:17.766402-04:00"
  },
  "latest_run": {
    "run_id": "occurrence-compiler-2026-04-16T23:19:11Z",
    "status": "completed",
    "compiled_packet_count": 267,
    "source_occurrence_count": 782,
    "completed_at": "2026-04-16T19:19:11.728069-04:00"
  }
}
